appledev/__init__.py
appledev/app.py
appledev-0.0.1.dist-info/METADATA
appledev-0.0.1.dist-info/WHEEL
appledev-0.0.1.dist-info/top_level.txt
appledev-0.0.1.dist-info/RECORD
