Metadata-Version: 2.1
Name: appledev
Version: 0.0.1
Summary: Apple AppStore Connect Api
Home-page: https://github.com/whdevlab/appledev
Author: WHDevLab
Author-email: whdevlab@163.com
License: MIT
Platform: UNKNOWN
Requires-Dist: requests
Requires-Dist: PyJWT
